denseCRF.cpython-36m-darwin.so
denseCRF3D.cpython-36m-darwin.so
maxflow.cpython-36m-darwin.so
SimpleCRF_binaries-0.2.1.2.dist-info/LICENSE
SimpleCRF_binaries-0.2.1.2.dist-info/METADATA
SimpleCRF_binaries-0.2.1.2.dist-info/WHEEL
SimpleCRF_binaries-0.2.1.2.dist-info/top_level.txt
SimpleCRF_binaries-0.2.1.2.dist-info/RECORD
