Metadata-Version: 2.1
Name: SimpleCRF-binaries
Version: 0.2.1.2
Summary: An open-source toolkit for conditional random field (CRF) and dense CRF
Home-page: https://github.com/andreped/SimpleCRF/tree/binaries
Author: Guotai Wang and André Pedersen
Author-email: wguotai@gmail.com
License: BSD
Platform: UNKNOWN
Classifier: License :: OSI Approved :: BSD License
Classifier: Programming Language :: Python :: 3 :: Only
Classifier: Programming Language :: Python :: 3.6
Classifier: Programming Language :: Python :: 3.7
Classifier: Programming Language :: Python :: 3.8
Classifier: Programming Language :: Python :: 3.9
Requires-Python: >=3.6
